envs/__init__.py
envs/babyrobot_v0.py
envs/babyrobot_v1.py
envs/cartpole.py
envs/helper/actions.py
envs/helper/babyrobot_v0_checker.py
envs/helper/babyrobot_v1_runner.py
brchengyu-1.0.0.dist-info/METADATA
brchengyu-1.0.0.dist-info/WHEEL
brchengyu-1.0.0.dist-info/top_level.txt
brchengyu-1.0.0.dist-info/RECORD
