Metadata-Version: 2.1
Name: brchengyu
Version: 1.0.0
Requires-Dist: gymnasium
